sqlalchemy_mptt-stubs/__init__.pyi
sqlalchemy_mptt-stubs/events.pyi
sqlalchemy_mptt-stubs/mixins.pyi
sqlalchemy_mptt-stubs/py.typed
sqlalchemy_mptt_stubs-0.0.4.dist-info/WHEEL
sqlalchemy_mptt_stubs-0.0.4.dist-info/METADATA
sqlalchemy_mptt_stubs-0.0.4.dist-info/RECORD
