Metadata-Version: 2.1
Name: sqlalchemy-mptt-stubs
Version: 0.0.4
Summary: Stubs for sqlalchemy_mptt
Home-page: https://github.com/ssfdust/sqlalchemy_mptt-stubs
License: MIT
Author: ssfdust
Author-email: ssfdust@gmail.com
Requires-Python: >=3.8,<4.0
Classifier: License :: OSI Approved :: MIT License
Classifier: Programming Language :: Python :: 3
Classifier: Programming Language :: Python :: 3.8
Classifier: Programming Language :: Python :: 3.9
Requires-Dist: sqlalchemy-stubs (>=0.4,<0.5)
Requires-Dist: sqlalchemy_mptt (>=0.2.5,<0.3.0)
Project-URL: Repository, https://github.com/ssfdust/sqlalchemy_mptt-stubs
